<?xml version="1.0" encoding="UTF-8"?>
<SchemaFile xmlns="" xmlns:xs="http://www.w3.org/2001/XMLSchema" xmlns:xsi="http://www.w3.org/2001/XMLSchema-instance">
	<dataCompositionSchema xmlns="http://v8.1c.ru/8.1/data-composition-system/schema">
		<dataSource>
			<name>ИсточникДанных1</name>
			<dataSourceType>Local</dataSourceType>
		</dataSource>
		<dataSet xsi:type="DataSetQuery">
			<name>НаборДанных1</name>
			<field xsi:type="DataSetFieldField">
				<dataPath>ДоговорКонтрагента</dataPath>
				<field>ДоговорКонтрагента</field>
			</field>
			<field xsi:type="DataSetFieldField">
				<dataPath>ЕдиницаИзмерения</dataPath>
				<field>ЕдиницаИзмерения</field>
			</field>
			<field xsi:type="DataSetFieldField">
				<dataPath>ЕстьНаСкладе</dataPath>
				<field>ЕстьНаСкладе</field>
				<title xmlns:d5p1="http://v8.1c.ru/8.1/data/core" xsi:type="d5p1:LocalStringType">
					<d5p1:item>
						<d5p1:lang>ru</d5p1:lang>
						<d5p1:content>Есть на складе Ангар ТЕСТ</d5p1:content>
					</d5p1:item>
				</title>
			</field>
			<field xsi:type="DataSetFieldField">
				<dataPath>ЗаказПокупателя</dataPath>
				<field>ЗаказПокупателя</field>
			</field>
			<field xsi:type="DataSetFieldField">
				<dataPath>ЗначениеУсловияАвтоматическойСкидки</dataPath>
				<field>ЗначениеУсловияАвтоматическойСкидки</field>
			</field>
			<field xsi:type="DataSetFieldField">
				<dataPath>Качество</dataPath>
				<field>Качество</field>
			</field>
			<field xsi:type="DataSetFieldField">
				<dataPath>Код</dataPath>
				<field>Код</field>
			</field>
			<field xsi:type="DataSetFieldField">
				<dataPath>Номенклатура</dataPath>
				<field>Номенклатура</field>
				<role>
					<dimension xmlns="http://v8.1c.ru/8.1/data-composition-system/common">true</dimension>
				</role>
			</field>
			<field xsi:type="DataSetFieldField">
				<dataPath>ПроцентАвтоматическихСкидок</dataPath>
				<field>ПроцентАвтоматическихСкидок</field>
			</field>
			<field xsi:type="DataSetFieldField">
				<dataPath>ПроцентСкидкиНаценки</dataPath>
				<field>ПроцентСкидкиНаценки</field>
			</field>
			<field xsi:type="DataSetFieldField">
				<dataPath>СерияНоменклатуры</dataPath>
				<field>СерияНоменклатуры</field>
			</field>
			<field xsi:type="DataSetFieldField">
				<dataPath>Склад</dataPath>
				<field>Склад</field>
			</field>
			<field xsi:type="DataSetFieldField">
				<dataPath>СтатусПартии</dataPath>
				<field>СтатусПартии</field>
			</field>
			<field xsi:type="DataSetFieldField">
				<dataPath>УсловиеАвтоматическойСкидки</dataPath>
				<field>УсловиеАвтоматическойСкидки</field>
			</field>
			<field xsi:type="DataSetFieldField">
				<dataPath>ХарактеристикаНоменклатуры</dataPath>
				<field>ХарактеристикаНоменклатуры</field>
			</field>
			<field xsi:type="DataSetFieldField">
				<dataPath>Цена</dataPath>
				<field>Цена</field>
			</field>
			<dataSource>ИсточникДанных1</dataSource>
			<query>ВЫБРАТЬ
	ТоварыНаСкладахОстатки.Номенклатура
ПОМЕСТИТЬ Ном
ИЗ
	РегистрНакопления.ТоварыНаСкладах.Остатки(, Склад = &amp;Склад) КАК ТоварыНаСкладахОстатки
;

////////////////////////////////////////////////////////////////////////////////
ВЫБРАТЬ
	ЗаказыПокупателейОстатки.Номенклатура,
	ВЫБОР
		КОГДА ЗаказыПокупателейОстатки.Номенклатура В
				(ВЫБРАТЬ
					ном.Номенклатура
				ИЗ
					Ном КАК ном)
			ТОГДА ИСТИНА
		ИНАЧЕ ЛОЖЬ
	КОНЕЦ КАК ЕстьНаСкладе,
	ЗаказыПокупателейОстатки.Номенклатура.Код КАК Код
ИЗ
	РегистрНакопления.ЗаказыПокупателей.Остатки(, ЗаказПокупателя = &amp;Заказ) КАК ЗаказыПокупателейОстатки</query>
		</dataSet>
		<parameter>
			<name>Период</name>
			<title xmlns:d4p1="http://v8.1c.ru/8.1/data/core" xsi:type="d4p1:LocalStringType">
				<d4p1:item>
					<d4p1:lang>ru</d4p1:lang>
					<d4p1:content>Период</d4p1:content>
				</d4p1:item>
			</title>
			<valueType>
				<Type xmlns="http://v8.1c.ru/8.1/data/core">xs:dateTime</Type>
				<DateQualifiers xmlns="http://v8.1c.ru/8.1/data/core">
					<DateFractions>DateTime</DateFractions>
				</DateQualifiers>
			</valueType>
			<value xsi:type="xs:dateTime">0001-01-01T00:00:00</value>
			<useRestriction>false</useRestriction>
		</parameter>
		<parameter>
			<name>Заказ</name>
			<title xmlns:d4p1="http://v8.1c.ru/8.1/data/core" xsi:type="d4p1:LocalStringType">
				<d4p1:item>
					<d4p1:lang>ru</d4p1:lang>
					<d4p1:content>Заказ</d4p1:content>
				</d4p1:item>
			</title>
			<valueType>
				<Type xmlns="http://v8.1c.ru/8.1/data/core" xmlns:d5p1="http://v8.1c.ru/8.1/data/enterprise/current-config">d5p1:DocumentRef.ЗаказПокупателя</Type>
			</valueType>
			<value xsi:nil="true"/>
			<useRestriction>true</useRestriction>
		</parameter>
		<parameter>
			<name>Склад</name>
			<title xmlns:d4p1="http://v8.1c.ru/8.1/data/core" xsi:type="d4p1:LocalStringType">
				<d4p1:item>
					<d4p1:lang>ru</d4p1:lang>
					<d4p1:content>Склад</d4p1:content>
				</d4p1:item>
			</title>
			<valueType>
				<Type xmlns="http://v8.1c.ru/8.1/data/core" xmlns:d5p1="http://v8.1c.ru/8.1/data/enterprise/current-config">d5p1:CatalogRef.Склады</Type>
			</valueType>
			<value xsi:nil="true"/>
			<useRestriction>true</useRestriction>
		</parameter>
		<settingsVariant>
			<name xmlns="http://v8.1c.ru/8.1/data-composition-system/settings">Основной</name>
			<presentation xmlns="http://v8.1c.ru/8.1/data-composition-system/settings" xsi:type="xs:string">Основной</presentation>
		</settingsVariant>
	</dataCompositionSchema>
</SchemaFile>﻿<?xml version="1.0" encoding="UTF-8"?>
<Settings xmlns="http://v8.1c.ru/8.1/data-composition-system/settings" xmlns:dcscor="http://v8.1c.ru/8.1/data-composition-system/core" xmlns:style="http://v8.1c.ru/8.1/data/ui/style" xmlns:sys="http://v8.1c.ru/8.1/data/ui/fonts/system" xmlns:v8="http://v8.1c.ru/8.1/data/core" xmlns:v8ui="http://v8.1c.ru/8.1/data/ui" xmlns:web="http://v8.1c.ru/8.1/data/ui/colors/web" xmlns:win="http://v8.1c.ru/8.1/data/ui/colors/windows" xmlns:xs="http://www.w3.org/2001/XMLSchema" xmlns:xsi="http://www.w3.org/2001/XMLSchema-instance">
	<order>
		<item xsi:type="OrderItemField">
			<field>Номенклатура</field>
			<orderType>Asc</orderType>
		</item>
	</order>
	<item xsi:type="StructureItemGroup">
		<groupItems>
			<item xsi:type="GroupItemField">
				<field>Код</field>
				<groupType>Items</groupType>
				<periodAdditionType>None</periodAdditionType>
				<periodAdditionBegin xsi:type="xs:dateTime">0001-01-01T00:00:00</periodAdditionBegin>
				<periodAdditionEnd xsi:type="xs:dateTime">0001-01-01T00:00:00</periodAdditionEnd>
			</item>
			<item xsi:type="GroupItemField">
				<field>Номенклатура</field>
				<groupType>Items</groupType>
				<periodAdditionType>None</periodAdditionType>
				<periodAdditionBegin xsi:type="xs:dateTime">0001-01-01T00:00:00</periodAdditionBegin>
				<periodAdditionEnd xsi:type="xs:dateTime">0001-01-01T00:00:00</periodAdditionEnd>
			</item>
			<item xsi:type="GroupItemField">
				<field>ЕстьНаСкладе</field>
				<groupType>Items</groupType>
				<periodAdditionType>None</periodAdditionType>
				<periodAdditionBegin xsi:type="xs:dateTime">0001-01-01T00:00:00</periodAdditionBegin>
				<periodAdditionEnd xsi:type="xs:dateTime">0001-01-01T00:00:00</periodAdditionEnd>
			</item>
		</groupItems>
		<order>
			<item xsi:type="OrderItemAuto"/>
		</order>
		<selection>
			<item xsi:type="SelectedItemAuto"/>
		</selection>
	</item>
</Settings>﻿<?xml version="1.0" encoding="UTF-8"?>
<SchemaFile xmlns="" xmlns:xs="http://www.w3.org/2001/XMLSchema" xmlns:xsi="http://www.w3.org/2001/XMLSchema-instance">
	<dataCompositionSchema xmlns="http://v8.1c.ru/8.1/data-composition-system/schema"/>
</SchemaFile>